mapapi/__init__.py
mapapi/baidu/__init__.py
mapapi/baidu/exceptions.py
mapapi/baidu/location_api.py
mapapi/baidu/place_api.py
mapapi/baidu/scheduler.py
mapapi/baidu/transform_api.py
mapapi-0.2.5.dist-info/METADATA
mapapi-0.2.5.dist-info/WHEEL
mapapi-0.2.5.dist-info/top_level.txt
mapapi-0.2.5.dist-info/RECORD
