Metadata-Version: 2.1
Name: mapapi
Version: 0.2.5
Summary: map web api, current support baidu
Home-page: https://github.com/starplanet/mapapi
Author: starplanet
Author-email: newvision1987@gmail.com
License: MIT
Keywords: map baidu
Requires-Dist: requests
